MANIFEST.in
README
README.rst
setup.py
shifter.py
shifter.egg-info/PKG-INFO
shifter.egg-info/SOURCES.txt
shifter.egg-info/dependency_links.txt
shifter.egg-info/top_level.txt