Metadata-Version: 1.0
Name: shifter
Version: 2.40
Summary: Transmission RPC Bindings
Home-page: https://github.com/terencehonles/shifter
Author: Terence Honles
Author-email: terence@honles.com
License: PSF
Keywords: Transmission RPC torrent
Platform: UNKNOWN
Classifier: Development Status :: 5 - Production/Stable
Classifier: Intended Audience :: Developers
Classifier: Intended Audience :: Information Technology
Classifier: Intended Audience :: System Administrators
Classifier: License :: OSI Approved :: Python Software Foundation License
Classifier: Operating System :: OS Independent
Classifier: Programming Language :: Python :: 2
Classifier: Programming Language :: Python :: 3
Classifier: Topic :: Software Development :: Libraries
